core/__init__.py
core/document.py
examples/__init__.py
examples/t.py
examples/usage.py
formats/__init__.py
formats/excel/__init__.py
formats/excel/excel_document.py
formats/markdown/__init__.py
formats/markdown/markdown_document.py
formats/text/__init__.py
formats/text/text_document.py
formats/word/__init__.py
formats/word/word_document.py
scribber/__init__.py
scribber/core/__init__.py
scribber/core/document.py
scribber/examples/__init__.py
scribber/examples/t.py
scribber/examples/usage.py
scribber/formats/__init__.py
scribber/formats/excel/__init__.py
scribber/formats/excel/excel_document.py
scribber/formats/markdown/__init__.py
scribber/formats/markdown/markdown_document.py
scribber/formats/text/__init__.py
scribber/formats/text/text_document.py
scribber/formats/word/__init__.py
scribber/formats/word/word_document.py
scribber-0.1.19.dist-info/LICENSE
scribber-0.1.19.dist-info/METADATA
scribber-0.1.19.dist-info/WHEEL
scribber-0.1.19.dist-info/top_level.txt
scribber-0.1.19.dist-info/RECORD
