Metadata-Version: 2.1
Name: scribber
Version: 0.1.19
Summary: A simple document generator with not very rich functionality that can export a document to some formats such as text, docx, xlsx and markdown.
Home-page: https://github.com/edelwi/scribber
Author: Evgeniy Semenov
Author-email: edelwi@yandex.ru
License: MIT
Classifier: Development Status :: 1 - Planning
Classifier: Programming Language :: Python :: 3
Classifier: License :: OSI Approved :: MIT License
Classifier: Operating System :: OS Independent
Requires-Python: >=3.10
License-File: LICENSE
Requires-Dist: lxml (<5.0.0,>=4.9.0)
Requires-Dist: pydantic (<2.0.0,>=1.10.2)
Requires-Dist: python-docx (<1.0.0,>=0.8.11)
Requires-Dist: typing-extensions (<5.0.0,>=4.4.0)
Requires-Dist: XlsxWriter (<4.0.0,>=3.0.3)
Provides-Extra: dev
Requires-Dist: twine (>=4.0.2) ; extra == 'dev'
